json_schema_validator/__init__.py
json_schema_validator/errors.py
json_schema_validator/extensions.py
json_schema_validator/misc.py
json_schema_validator/schema.py
json_schema_validator/shortcuts.py
json_schema_validator/validator.py
json_schema_validator/tests/__init__.py
json_schema_validator/tests/test_extensions.py
json_schema_validator/tests/test_schema.py
json_schema_validator/tests/test_validator.py
json_schema_validator-2.4.dist-info/DESCRIPTION.rst
json_schema_validator-2.4.dist-info/METADATA
json_schema_validator-2.4.dist-info/RECORD
json_schema_validator-2.4.dist-info/WHEEL
json_schema_validator-2.4.dist-info/metadata.json
json_schema_validator-2.4.dist-info/top_level.txt
json_schema_validator-2.4.dist-info/zip-safe
