Metadata-Version: 2.0
Name: json-schema-validator
Version: 2.4
Summary: JSON Schema Validator
Home-page: https://github.com/zyga/json-schema-validator
Author: Zygmunt Krynicki
Author-email: me@zygoon.pl
License: UNKNOWN
Platform: UNKNOWN
Classifier: Development Status :: 4 - Beta
Classifier: Intended Audience :: Developers
Classifier: License :: OSI Approved :: GNU Library or Lesser General Public License (LGPL)
Classifier: Operating System :: OS Independent
Classifier: Programming Language :: Python :: 2.6
Classifier: Programming Language :: Python :: 2.7
Classifier: Programming Language :: Python :: 3
Classifier: Programming Language :: Python :: 3.3
Classifier: Programming Language :: Python :: 3.4
Classifier: Programming Language :: Python :: 3.5
Requires-Dist: simplejson (>=2.0.9)
